{
"selfNodeId start from 1": "",
    "selfNodeId": 1,
    "buffer 300000(2GB) - 65536000(distribute 500GB)/41943040(single 320GB)(1000 warehouse)": "",
    "buffer": 300000,
    "bufferLruPartition 100": "",
    "bufferLruPartition": 100,
    "checkpointTimeout 60": "",
    "checkpointTimeout": 60,
    "defaultIsolationLevel 0": "",
    "defaultIsolationLevel": 0,
    "maintenanceWorkMem 2097152(2GB)": "",
    "maintenanceWorkMem": 2097152,
    "dataDir": "",
    "ncores 800-2000(1000 warehouse)": "",
    "ncores": 800,
    "logMinMessages DSTORE_DEBUG1(1) DSTORE_INFO(3)": "",
    "logMinMessages": 3,
    "foldPeriod (seconds)": "",
    "foldPeriod": 20,
    "foldThreshold (num)": "",
    "foldThreshold": 10,
    "foldLevel DSTORE_WARNING(5)": "",
    "foldLevel": 5,
    "csnAssignmentIncrement 10000(distribute) 1000(single)": "",
    "csnAssignmentIncrement": 1000,
    "moduleLoggingConfigure null": "",
    "moduleLoggingConfigure": "",
    "lockHashTableSize 256": "",
    "lockHashTableSize": 256,
    "lockTablePartitionNum 256": "",
    "lockTablePartitionNum": 256,
    "enableLazyLock false": "",
    "enableLazyLock": false,
    "vfsConfigPath null": "",
    "vfsConfigPath": "",
    "vfsTenantIsolationConfigPath null": "",
    "vfsTenantIsolationConfigPath": "",
    "updateCsnMinInterval 10(distribute) 500000(single 500ms)": "",
    "updateCsnMinInterval": 500000,
    "numObjSpaceMgrWorkers 1": "",
    "numObjSpaceMgrWorkers": 1,
    "minFreePagePercentageThreshold1 50(distribute) 0(single)": "",
    "minFreePagePercentageThreshold1": 0,
    "minFreePagePercentageThreshold2 20(distribute) 0(single)": "", 
    "minFreePagePercentageThreshold2": 0,
    "probOfExtensionThreshold 1(distribute) 0(single)": "",
    "probOfExtensionThreshold": 0,
    "recoveryWorkerNum": 1,
    "synchronousCommit true": "",
    "synchronousCommit": true,
    "walStreamCount 10": "",
    "walStreamCount": 10,
    "walFileNumber 1": "",
    "walFileNumber": 1,
    "walFileSize 3221225472(Byte)": "",
    "walFileSize": "3221225472",
    "walBuffers Byte 1048576(distribute) 16384(single)": "",
    "walBuffers": 16384,
    "walReadBufferSize 536870912(Byte)": "",
    "walReadBufferSize": "536870912",
    "walRedoBufferSize 268435456(Byte)": "",
    "walRedoBufferSize": "268435456",
    "walwriterCpuBind -1(distribute) 0(single)": "",
    "walwriterCpuBind": 0,
    "redoBindCpuAttr nobind": "",
    "redoBindCpuAttr": "nobind",
    "numaNodeNum 1": "",
    "numaNodeNum": 1,
    "disableBtreePageRecycle false": "",
    "disableBtreePageRecycle": false,
    "deadlockTimeInterval 20000": "",
    "deadlockTimeInterval": 20000,
    "recycleFsmTimeInterval 1440": "",
    "recycleFsmTimeInterval": 1440,
    "probOfUpdateFsmTimestamp 10": "",
    "probOfUpdateFsmTimestamp": 10,
    "probOfRecycleFsm 0": "",
    "probOfRecycleFsm": 0,
    "probOfRecycleBtree 0": "",
    "probOfRecycleBtree": 0,
    "distLockNumBuckets 1024": "",
    "distLockNumBuckets": 1024,
    "distLockMaxRingSize 1024": "",
    "distLockMaxRingSize": 1024,
    "csnMode 0:DEFAULT 1:BROADCAST 2:GLOBAL_CLOCK": "",
    "csnMode": 0,
    "ctrlPlanePort 11830": "",
    "ctrlPlanePort": 11830,
    "rdmaGidIndex 3": "",
    "rdmaGidIndex": 3,
    "rdmaIbPort 1": "",
    "rdmaIbPort": 1,
    "rdmaDeviceName mlx5_1": "",
    "rdmaDeviceName": "mlx5_1",
    "pdReadAuthResetPeriod 30": "",
    "pdReadAuthResetPeriod": 30,
    "schedulerBaseListenPort 1116": "",
    "schedulerBaseListenPort": 1116,
    "csnThreadBindCpu -1": "",
    "csnThreadBindCpu": -1,
    "commConfigStr null": "",
    "commConfigStr": "",
    "memberView null": "",
    "memberView": "",
    "commProtocolTypeStr TCP_TYPE": "",
    "commProtocolTypeStr": "TCP_TYPE",
    "commProtocolType 0": "",
    "commProtocolType": 0,
    "globalClockAdjustWaitTimeUs 250": "",
    "globalClockAdjustWaitTimeUs": 250,
    "globalClockSyncIntervalMs 5": "",
    "globalClockSyncIntervalMs": 5,
    "gclockOverlapWaitTimeOptimization true": "",
    "gclockOverlapWaitTimeOptimization": true,
    "defaultHeartbeatTimeoutInterval 1": "",
    "defaultHeartbeatTimeoutInterval": 1,
    "defaultWalSizeThreshold 1": "",
    "defaultWalSizeThreshold": 1,
    "commThreadMin" : 30,
    "commThreadMax" : 50,
    "clusterId" : 1,
    "enableQuickStartUp true": "",
    "enableQuickStartUp": true,
    "startConfigPath": "",
    "bgDiskWriterSlaveNum" : 1,
    "bgPageWriterSleepMilliSecond" : 2000,
    "walThrottlingSize" : 1048576,
    "maxIoCapacityKb" : 512000,
    "bgWalWriterMinBytes 51200(Byte)": "",
    "bgWalWriterMinBytes": "51200",
    "walEachWriteLenghthLimit 524288(Byte)": "",
    "walEachWriteLenghthLimit": "524288"
}
